dbbasic/__init__.py
dbbasic/admin.py
dbbasic/audit_log.py
dbbasic/bigtable_tsv.py
dbbasic/tsv.py
dbbasic/tsv_accelerated.py
dbbasic_tsv-1.0.2.dist-info/licenses/LICENSE
dbbasic_tsv-1.0.2.dist-info/METADATA
dbbasic_tsv-1.0.2.dist-info/WHEEL
dbbasic_tsv-1.0.2.dist-info/top_level.txt
dbbasic_tsv-1.0.2.dist-info/RECORD
