Metadata-Version: 2.4
Name: dbbasic-tsv
Version: 1.0.2
Summary: A pure-Python, filesystem-based database using TSV files
Home-page: https://github.com/askrobots/dbbasic-tsv
Author: AskRobots Contributors
License: MIT
Project-URL: Homepage, https://github.com/askrobots/dbbasic-tsv
Project-URL: Documentation, https://github.com/askrobots/dbbasic-tsv#readme
Project-URL: Repository, https://github.com/askrobots/dbbasic-tsv
Project-URL: Issues, https://github.com/askrobots/dbbasic-tsv/issues
Keywords: database,tsv,filesystem,nosql,embedded,portable
Classifier: Development Status :: 5 - Production/Stable
Classifier: Intended Audience :: Developers
Classifier: Topic :: Database
Classifier: Topic :: Software Development :: Libraries :: Python Modules
Classifier: License :: OSI Approved :: MIT License
Classifier: Programming Language :: Python :: 3
Classifier: Programming Language :: Python :: 3.7
Classifier: Programming Language :: Python :: 3.8
Classifier: Programming Language :: Python :: 3.9
Classifier: Programming Language :: Python :: 3.10
Classifier: Programming Language :: Python :: 3.11
Classifier: Operating System :: OS Independent
Requires-Python: >=3.7
License-File: LICENSE
Provides-Extra: dev
Requires-Dist: pytest>=7.0; extra == "dev"
Requires-Dist: pytest-cov>=4.0; extra == "dev"
Requires-Dist: black>=22.0; extra == "dev"
Requires-Dist: isort>=5.0; extra == "dev"
Requires-Dist: flake8>=5.0; extra == "dev"
Dynamic: home-page
Dynamic: license-file
Dynamic: requires-python
